viger/__init__.py
viger/tool/__init__.py
viger/tool/encryption.py
viger/tool/json.py
viger/tool/mail.py
viger/tool/timer.py
viger/tool/logging/__init__.py
viger/tool/logging/config.py
viger/tool/logging/handlers.py
viger_tool-0.0.15.dist-info/METADATA
viger_tool-0.0.15.dist-info/WHEEL
viger_tool-0.0.15.dist-info/top_level.txt
viger_tool-0.0.15.dist-info/RECORD
